altcha/__init__.py
altcha/altcha.py
altcha/py.typed
altcha-1.0.0.dist-info/licenses/LICENSE
altcha-1.0.0.dist-info/METADATA
altcha-1.0.0.dist-info/WHEEL
altcha-1.0.0.dist-info/top_level.txt
altcha-1.0.0.dist-info/RECORD
