Metadata-Version: 2.4
Name: altcha
Version: 1.0.0
Summary: A library for creating and verifying challenges for ALTCHA.
Home-page: https://github.com/altcha-org/altcha-lib-py
Author: Daniel Regeci
Author-email: 536331+ovx@users.noreply.github.com
Classifier: Programming Language :: Python :: 3
Classifier: License :: OSI Approved :: MIT License
Classifier: Operating System :: OS Independent
Requires-Python: >=3.9
License-File: LICENSE
Dynamic: author
Dynamic: author-email
Dynamic: classifier
Dynamic: description
Dynamic: description-content-type
Dynamic: home-page
Dynamic: license-file
Dynamic: requires-python
Dynamic: summary
